boss/.directory
boss/BOSS.py
boss/__init__.py
boss/_cli_base.py
boss/batch.py
boss/config.py
boss/core.py
boss/dependencies.py
boss/dynamic_readfish.py
boss/live.py
boss/mapper.py
boss/paf.py
boss/readfish_boss.py
boss/readlengthdist.py
boss/sampler.py
boss/snippet.py
boss/utils.py
boss/aeons/.directory
boss/aeons/__init__.py
boss/aeons/core.py
boss/aeons/kmer.py
boss/aeons/repeats.py
boss/aeons/sequences.py
boss/aeons/simulation.py
boss/runs/.directory
boss/runs/__init__.py
boss/runs/abundance_tracker.py
boss/runs/core.py
boss/runs/readstartdist.py
boss/runs/reference.py
boss/runs/sequences.py
boss/runs/simulation.py
boss_runs-0.3.2.dist-info/METADATA
boss_runs-0.3.2.dist-info/WHEEL
boss_runs-0.3.2.dist-info/entry_points.txt
boss_runs-0.3.2.dist-info/licenses/LICENSE
boss_runs-0.3.2.dist-info/RECORD
