Metadata-Version: 2.4
Name: boss_runs
Version: 0.3.2
Summary: Dynamic, adaptive sampling during nanopore sequencing
Project-URL: homepage, https://github.com/goldman-gp-ebi/BOSS-RUNS/
License-File: LICENSE
Requires-Python: <3.13,>=3.10
Requires-Dist: bottleneck~=1.3.7
Requires-Dist: mappy~=2.28
Requires-Dist: numba~=0.59.0
Requires-Dist: psutil~=7.0.0
Requires-Dist: readfish[all]==2024.3.0
Requires-Dist: scipy~=1.12.0
Provides-Extra: dev
Requires-Dist: pytest-cov~=4.1.0; extra == 'dev'
Requires-Dist: pytest-timeout~=2.2.0; extra == 'dev'
Requires-Dist: pytest~=8.0.0; extra == 'dev'
